panelbox/__init__.py
panelbox/__version__.py
panelbox/cli/__init__.py
panelbox/cli/{commands}/__init__.py
panelbox/core/__init__.py
panelbox/core/base_model.py
panelbox/core/formula_parser.py
panelbox/core/panel_data.py
panelbox/core/results.py
panelbox/datasets/__init__.py
panelbox/datasets/{data}/__init__.py
panelbox/gmm/__init__.py
panelbox/gmm/difference_gmm.py
panelbox/gmm/estimator.py
panelbox/gmm/instruments.py
panelbox/gmm/results.py
panelbox/gmm/system_gmm.py
panelbox/gmm/tests.py
panelbox/models/__init__.py
panelbox/models/dynamic/__init__.py
panelbox/models/iv/__init__.py
panelbox/models/static/__init__.py
panelbox/models/static/fixed_effects.py
panelbox/models/static/pooled_ols.py
panelbox/models/static/random_effects.py
panelbox/report/__init__.py
panelbox/report/asset_manager.py
panelbox/report/css_manager.py
panelbox/report/report_manager.py
panelbox/report/template_manager.py
panelbox/report/validation_transformer.py
panelbox/report/exporters/__init__.py
panelbox/report/exporters/html_exporter.py
panelbox/report/exporters/latex_exporter.py
panelbox/report/exporters/markdown_exporter.py
panelbox/report/renderers/__init__.py
panelbox/report/renderers/static_validation_renderer.py
panelbox/report/renderers/static/__init__.py
panelbox/report/transformers/__init__.py
panelbox/report/transformers/static/__init__.py
panelbox/standard_errors/__init__.py
panelbox/templates/__init__.py
panelbox/templates/assets/css/base_styles.css
panelbox/templates/assets/css/report_components.css
panelbox/templates/assets/js/tab-navigation.js
panelbox/templates/assets/js/utils.js
panelbox/templates/common/footer.html
panelbox/templates/common/header.html
panelbox/templates/common/meta.html
panelbox/templates/validation/interactive/index.html
panelbox/templates/validation/interactive/partials/charts.html
panelbox/templates/validation/interactive/partials/methodology.html
panelbox/templates/validation/interactive/partials/overview.html
panelbox-0.2.0.dist-info/licenses/LICENSE
panelbox-0.2.0.dist-info/METADATA
panelbox-0.2.0.dist-info/WHEEL
panelbox-0.2.0.dist-info/entry_points.txt
panelbox-0.2.0.dist-info/top_level.txt
panelbox-0.2.0.dist-info/RECORD
