Metadata-Version: 2.4
Name: panelbox
Version: 0.2.0
Summary: Panel data econometrics in Python: Fixed Effects, Random Effects, GMM (Arellano-Bond, Blundell-Bond)
Author-email: Gustavo Haase <gustavo.haase@gmail.com>, Paulo Dourado <paulodourado.unb@gmail.com>
License: MIT
Project-URL: Homepage, https://github.com/PanelBox-Econometrics-Model/panelbox
Project-URL: Documentation, https://github.com/PanelBox-Econometrics-Model/panelbox/tree/main/docs
Project-URL: Repository, https://github.com/PanelBox-Econometrics-Model/panelbox
Project-URL: Issues, https://github.com/PanelBox-Econometrics-Model/panelbox/issues
Project-URL: Changelog, https://github.com/PanelBox-Econometrics-Model/panelbox/blob/main/CHANGELOG.md
Keywords: econometrics,panel data,GMM,Arellano-Bond,Blundell-Bond,fixed effects,random effects,dynamic panel,instrumental variables
Classifier: Development Status :: 4 - Beta
Classifier: Intended Audience :: Science/Research
Classifier: Intended Audience :: Financial and Insurance Industry
Classifier: License :: OSI Approved :: MIT License
Classifier: Operating System :: OS Independent
Classifier: Programming Language :: Python :: 3
Classifier: Programming Language :: Python :: 3.9
Classifier: Programming Language :: Python :: 3.10
Classifier: Programming Language :: Python :: 3.11
Classifier: Programming Language :: Python :: 3.12
Classifier: Topic :: Scientific/Engineering
Classifier: Topic :: Scientific/Engineering :: Mathematics
Classifier: Topic :: Office/Business :: Financial
Requires-Python: >=3.9
License-File: LICENSE
Requires-Dist: numpy>=1.24.0
Requires-Dist: pandas>=2.0.0
Requires-Dist: scipy>=1.10.0
Requires-Dist: statsmodels>=0.14.0
Requires-Dist: patsy>=0.5.3
Provides-Extra: dev
Requires-Dist: pytest>=7.3.0; extra == "dev"
Requires-Dist: pytest-cov>=4.1.0; extra == "dev"
Requires-Dist: black>=23.3.0; extra == "dev"
Requires-Dist: flake8>=6.0.0; extra == "dev"
Requires-Dist: mypy>=1.3.0; extra == "dev"
Requires-Dist: isort>=5.12.0; extra == "dev"
Provides-Extra: docs
Requires-Dist: mkdocs>=1.4.0; extra == "docs"
Requires-Dist: mkdocs-material>=9.1.0; extra == "docs"
Requires-Dist: mkdocstrings>=0.22.0; extra == "docs"
Requires-Dist: mkdocstrings-python>=1.1.0; extra == "docs"
Provides-Extra: test
Requires-Dist: pytest>=7.3.0; extra == "test"
Requires-Dist: pytest-cov>=4.1.0; extra == "test"
Requires-Dist: hypothesis>=6.75.0; extra == "test"
Dynamic: license-file
